LICENSE
MANIFEST.in
README
setup.py
xtermcolor/ColorMap.py
xtermcolor/Main.py
xtermcolor/__init__.py
xtermcolor/distribute_setup.py
xtermcolor.egg-info/PKG-INFO
xtermcolor.egg-info/SOURCES.txt
xtermcolor.egg-info/dependency_links.txt
xtermcolor.egg-info/entry_points.txt
xtermcolor.egg-info/top_level.txt