Metadata-Version: 1.0
Name: xtermcolor
Version: 1.0.4
Summary: Python module for colorizing output with xterm 256 color support
